odoo/addons/website_prevent_cls/README.rst
odoo/addons/website_prevent_cls/__init__.py
odoo/addons/website_prevent_cls/__manifest__.py
odoo/addons/website_prevent_cls/i18n/website_prevent_cls.pot
odoo/addons/website_prevent_cls/models/__init__.py
odoo/addons/website_prevent_cls/models/ir_qweb_fields.py
odoo/addons/website_prevent_cls/readme/CONTRIBUTORS.rst
odoo/addons/website_prevent_cls/readme/DESCRIPTION.rst
odoo/addons/website_prevent_cls/readme/ROADMAP.rst
odoo/addons/website_prevent_cls/readme/USAGE.rst
odoo/addons/website_prevent_cls/static/description/icon.png
odoo/addons/website_prevent_cls/static/description/index.html
odoo/addons/website_prevent_cls/static/src/js/alt_dialog.js
odoo/addons/website_prevent_cls/static/src/js/widget_media.js
odoo/addons/website_prevent_cls/static/src/xml/alt_dialog.xml
odoo/addons/website_prevent_cls/templates/assets.xml
odoo13_addon_website_prevent_cls-13.0.2.0.1.dist-info/METADATA
odoo13_addon_website_prevent_cls-13.0.2.0.1.dist-info/WHEEL
odoo13_addon_website_prevent_cls-13.0.2.0.1.dist-info/top_level.txt
odoo13_addon_website_prevent_cls-13.0.2.0.1.dist-info/RECORD
